Workbook

Sheet Summary
A1: Question type | B1: What it covers | C1: All examples | D1: Share of all | E1: Train | F1: Test | G1: Picked: even spread (n=15) | H1: Picked: balanced (n=15)
A2: Progress update (high intent) | B2: Signed up, uploading, paying, travelling: ready to proceed | C2: =COUNTIF(Questions!$E$2:$E$129,A2) -> 16 | D2: =IF($C$15=0,0,C2/$C$15) -> 0.125 | E2: =COUNTIFS(Questions!$E$2:$E$129,A2,Questions!$D$2:$D$129,"Train") -> 9 | F2: =COUNTIFS(Questions!$E$2:$E$129,A2,Questions!$D$2:$D$129,"Test") -> 7 | G2: =COUNTIFS(Questions!$E$2:$E$129,A2,Questions!$F$2:$F$129,"Yes") -> 3 | H2: =COUNTIFS(Questions!$E$2:$E$129,A2,Questions!$G$2:$G$129,"Yes") -> 1
A3: Documents | B3: Which documents, translations, address proof, photos, formats | C3: =COUNTIF(Questions!$E$2:$E$129,A3) -> 15 | D3: =IF($C$15=0,0,C3/$C$15) -> 0.1171875 | E3: =COUNTIFS(Questions!$E$2:$E$129,A3,Questions!$D$2:$D$129,"Train") -> 11 | F3: =COUNTIFS(Questions!$E$2:$E$129,A3,Questions!$D$2:$D$129,"Test") -> 4 | G3: =COUNTIFS(Questions!$E$2:$E$129,A3,Questions!$F$2:$F$129,"Yes") -> 3 | H3: =COUNTIFS(Questions!$E$2:$E$129,A3,Questions!$G$2:$G$129,"Yes") -> 1
A4: Where & how to apply | B4: Eligibility, which country/embassy, visa type, switching from tourist visa | C4: =COUNTIF(Questions!$E$2:$E$129,A4) -> 14 | D4: =IF($C$15=0,0,C4/$C$15) -> 0.109375 | E4: =COUNTIFS(Questions!$E$2:$E$129,A4,Questions!$D$2:$D$129,"Train") -> 9 | F4: =COUNTIFS(Questions!$E$2:$E$129,A4,Questions!$D$2:$D$129,"Test") -> 5 | G4: =COUNTIFS(Questions!$E$2:$E$129,A4,Questions!$F$2:$F$129,"Yes") -> 2 | H4: =COUNTIFS(Questions!$E$2:$E$129,A4,Questions!$G$2:$G$129,"Yes") -> 1
A5: After approval & staying | B5: TDAC, re-entry, 180-day stays, border runs, 90-day reporting, work rules | C5: =COUNTIF(Questions!$E$2:$E$129,A5) -> 13 | D5: =IF($C$15=0,0,C5/$C$15) -> 0.1015625 | E5: =COUNTIFS(Questions!$E$2:$E$129,A5,Questions!$D$2:$D$129,"Train") -> 6 | F5: =COUNTIFS(Questions!$E$2:$E$129,A5,Questions!$D$2:$D$129,"Test") -> 7 | G5: =COUNTIFS(Questions!$E$2:$E$129,A5,Questions!$F$2:$F$129,"Yes") -> 1 | H5: =COUNTIFS(Questions!$E$2:$E$129,A5,Questions!$G$2:$G$129,"Yes") -> 1
A6: Sharing situation | B6: Introduces themselves or answers the consultant's questions | C6: =COUNTIF(Questions!$E$2:$E$129,A6) -> 12 | D6: =IF($C$15=0,0,C6/$C$15) -> 0.09375 | E6: =COUNTIFS(Questions!$E$2:$E$129,A6,Questions!$D$2:$D$129,"Train") -> 9 | F6: =COUNTIFS(Questions!$E$2:$E$129,A6,Questions!$D$2:$D$129,"Test") -> 3 | G6: =COUNTIFS(Questions!$E$2:$E$129,A6,Questions!$F$2:$F$129,"Yes") -> 2 | H6: =COUNTIFS(Questions!$E$2:$E$129,A6,Questions!$G$2:$G$129,"Yes") -> 1
A7: Timeline & processing | B7: Processing times, how long to stay, urgency | C7: =COUNTIF(Questions!$E$2:$E$129,A7) -> 11 | D7: =IF($C$15=0,0,C7/$C$15) -> 0.0859375 | E7: =COUNTIFS(Questions!$E$2:$E$129,A7,Questions!$D$2:$D$129,"Train") -> 6 | F7: =COUNTIFS(Questions!$E$2:$E$129,A7,Questions!$D$2:$D$129,"Test") -> 5 | G7: =COUNTIFS(Questions!$E$2:$E$129,A7,Questions!$F$2:$F$129,"Yes") -> 0 | H7: =COUNTIFS(Questions!$E$2:$E$129,A7,Questions!$G$2:$G$129,"Yes") -> 1
A8: Fees & guarantee | B8: Service fees, government fees, money-back guarantee | C8: =COUNTIF(Questions!$E$2:$E$129,A8) -> 10 | D8: =IF($C$15=0,0,C8/$C$15) -> 0.078125 | E8: =COUNTIFS(Questions!$E$2:$E$129,A8,Questions!$D$2:$D$129,"Train") -> 4 | F8: =COUNTIFS(Questions!$E$2:$E$129,A8,Questions!$D$2:$D$129,"Test") -> 6 | G8: =COUNTIFS(Questions!$E$2:$E$129,A8,Questions!$F$2:$F$129,"Yes") -> 0 | H8: =COUNTIFS(Questions!$E$2:$E$129,A8,Questions!$G$2:$G$129,"Yes") -> 1
A9: Bank balance & finances | B9: 500,000 THB rule, crypto, stocks, currency | C9: =COUNTIF(Questions!$E$2:$E$129,A9) -> 9 | D9: =IF($C$15=0,0,C9/$C$15) -> 0.0703125 | E9: =COUNTIFS(Questions!$E$2:$E$129,A9,Questions!$D$2:$D$129,"Train") -> 7 | F9: =COUNTIFS(Questions!$E$2:$E$129,A9,Questions!$D$2:$D$129,"Test") -> 2 | G9: =COUNTIFS(Questions!$E$2:$E$129,A9,Questions!$F$2:$F$129,"Yes") -> 2 | H9: =COUNTIFS(Questions!$E$2:$E$129,A9,Questions!$G$2:$G$129,"Yes") -> 1
A10: Thanks & closing | B10: Thank-yous, sign-offs, encouragement | C10: =COUNTIF(Questions!$E$2:$E$129,A10) -> 8 | D10: =IF($C$15=0,0,C10/$C$15) -> 0.0625 | E10: =COUNTIFS(Questions!$E$2:$E$129,A10,Questions!$D$2:$D$129,"Train") -> 7 | F10: =COUNTIFS(Questions!$E$2:$E$129,A10,Questions!$D$2:$D$129,"Test") -> 1 | G10: =COUNTIFS(Questions!$E$2:$E$129,A10,Questions!$F$2:$F$129,"Yes") -> 0 | H10: =COUNTIFS(Questions!$E$2:$E$129,A10,Questions!$G$2:$G$129,"Yes") -> 1
A11: Embassy interview | B11: Preparing for an in-person embassy interview | C11: =COUNTIF(Questions!$E$2:$E$129,A11) -> 7 | D11: =IF($C$15=0,0,C11/$C$15) -> 0.0546875 | E11: =COUNTIFS(Questions!$E$2:$E$129,A11,Questions!$D$2:$D$129,"Train") -> 7 | F11: =COUNTIFS(Questions!$E$2:$E$129,A11,Questions!$D$2:$D$129,"Test") -> 0 | G11: =COUNTIFS(Questions!$E$2:$E$129,A11,Questions!$F$2:$F$129,"Yes") -> 2 | H11: =COUNTIFS(Questions!$E$2:$E$129,A11,Questions!$G$2:$G$129,"Yes") -> 1
A12: Payment | B12: Paying, payment problems, bank transfer | C12: =COUNTIF(Questions!$E$2:$E$129,A12) -> 6 | D12: =IF($C$15=0,0,C12/$C$15) -> 0.046875 | E12: =COUNTIFS(Questions!$E$2:$E$129,A12,Questions!$D$2:$D$129,"Train") -> 3 | F12: =COUNTIFS(Questions!$E$2:$E$129,A12,Questions!$D$2:$D$129,"Test") -> 3 | G12: =COUNTIFS(Questions!$E$2:$E$129,A12,Questions!$F$2:$F$129,"Yes") -> 0 | H12: =COUNTIFS(Questions!$E$2:$E$129,A12,Questions!$G$2:$G$129,"Yes") -> 2
A13: DTV rules & eligibility | B13: What the visa allows: Thai clients, beginners, exceptions to rules | C13: =COUNTIF(Questions!$E$2:$E$129,A13) -> 4 | D13: =IF($C$15=0,0,C13/$C$15) -> 0.03125 | E13: =COUNTIFS(Questions!$E$2:$E$129,A13,Questions!$D$2:$D$129,"Train") -> 4 | F13: =COUNTIFS(Questions!$E$2:$E$129,A13,Questions!$D$2:$D$129,"Test") -> 0 | G13: =COUNTIFS(Questions!$E$2:$E$129,A13,Questions!$F$2:$F$129,"Yes") -> 0 | H13: =COUNTIFS(Questions!$E$2:$E$129,A13,Questions!$G$2:$G$129,"Yes") -> 1
A14: Rejection & reapplication | B14: Visa was refused; can they reapply and where | C14: =COUNTIF(Questions!$E$2:$E$129,A14) -> 3 | D14: =IF($C$15=0,0,C14/$C$15) -> 0.0234375 | E14: =COUNTIFS(Questions!$E$2:$E$129,A14,Questions!$D$2:$D$129,"Train") -> 3 | F14: =COUNTIFS(Questions!$E$2:$E$129,A14,Questions!$D$2:$D$129,"Test") -> 0 | G14: =COUNTIFS(Questions!$E$2:$E$129,A14,Questions!$F$2:$F$129,"Yes") -> 0 | H14: =COUNTIFS(Questions!$E$2:$E$129,A14,Questions!$G$2:$G$129,"Yes") -> 2
A15: Total | C15: =SUM(C2:C14) -> 128 | D15: =SUM(D2:D14) -> 1 | E15: =SUM(E2:E14) -> 85 | F15: =SUM(F2:F14) -> 43 | G15: =SUM(G2:G14) -> 15 | H15: =SUM(H2:H14) -> 15
A16: Question types covered | G16: =COUNTIF(G2:G14,">0") -> 7 | H16: =COUNTIF(H2:H14,">0") -> 13
A18: How to read this
A19: One row per client turn: the client's message(s) that a real consultant then replied to (128 turns from 15 conversations).
A20: Question types come from keyword rules in app/categories.py (see the 'Type rules' sheet). They are deterministic, so the same message always gets the same type.
A21: Test = conversations held out from training (SYNTH_011, SYNTH_012, SYNTH_013, SYNTH_014, SYNTH_015).
A22: The last two columns compare two ways of choosing training examples. Even spread follows the data's natural mix. Balanced takes examples round-robin across types, rarest first, so rare situations (rejections, interviews) are included, in the same spirit as oversampling rare classes in image detection, without duplicating any example.

Sheet Questions
A1: # | B1: Conversation | C1: Scenario | D1: Split | E1: Question type | F1: Picked: even spread | G1: Picked: balanced | H1: Client message(s) | I1: Real consultant reply
A2: 1 | B2: SYNTH_001 | C2: First-time DTV applicant - Digital Nomad (Remote Worker) | D2: Train | E2: Sharing situation | F2: Yes | G2: Yes | H2: Hello, I'm interested in the DTV visa for Thailand. I work remotely as a software developer for a US company. | I2: Hi there! Thank you for reaching out. The DTV (Destination Thailand Visa) is perfect for remote workers like yourself. May I know your nationality and which country you'd like to apply from?
A3: 2 | B3: SYNTH_001 | C3: First-time DTV applicant - Digital Nomad (Remote Worker) | D3: Train | E3: Where & how to apply | F3: No | G3: Yes | H3: I'm American and currently in Bali. Can I apply from Indonesia? | I3: Yes, you can apply from Indonesia! For remote workers, our service fees are 18,000 THB including all government fees. The processing time in Indonesia is typically around 10 business days.
A4: 3 | B4: SYNTH_001 | C4: First-time DTV applicant - Digital Nomad (Remote Worker) | D4: Train | E4: Documents | F4: No | G4: Yes | H4: What documents do I need to prepare? | I4: For remote workers applying for the DTV, you'll need: 1. Valid passport with at least 6 months validity 2. Bank statements showing 500,000 THB equivalent for the past 3 months 3. Employment contract or letter from your employer confirming remote work arrangement 4. Proof of income (pay slips from the last 3 months) 5. Passport-sized photo 6. Proof of address in your submission country
A5: 4 | B5: SYNTH_001 | C5: First-time DTV applicant - Digital Nomad (Remote Worker) | D5: Train | E5: Bank balance & finances | F5: No | G5: Yes | H5: I have all those. My bank balance has been above $15,000 USD for the past year actually. Do I need to convert it to THB? | I5: No need to convert! As long as your bank statements show the equivalent of 500,000 THB (approximately $14,000-15,000 USD), that's acceptable. Please make sure the statements clearly show your name and the balance over the 3-month period.
A6: 5 | B6: SYNTH_001 | C6: First-time DTV applicant - Digital Nomad (Remote Worker) | D6: Train | E6: Where & how to apply | F6: No | G6: No | H6: Perfect. How do I get started? | I6: Please download our app and create an account. You can upload all your documents there, and our legal team will review them within 1-2 business days. Once approved, we'll guide you through the payment and submission process. App link: [APP_LINK]
A7: 6 | B7: SYNTH_001 | C7: First-time DTV applicant - Digital Nomad (Remote Worker) | D7: Train | E7: Progress update (high intent) | F7: Yes | G7: Yes | H7: Downloaded and signed up. Email is [EMAIL]. Uploading docs now. | I7: Great! I can see your account. Please upload all documents and we'll review them shortly. One important reminder: please make sure to maintain the 500,000 THB balance in your account until your visa is approved, as the embassy may request an updated statement.
A8: 7 | B8: SYNTH_001 | C8: First-time DTV applicant - Digital Nomad (Remote Worker) | D8: Train | E8: Timeline & processing | F8: No | G8: Yes | H8: Done! All uploaded. How long do I need to stay in Indonesia while waiting? | I8: According to official regulations, you should remain in Indonesia until the visa is approved. If you leave before your visa is issued, we won't be able to extend our money-back guarantee. Processing typically takes about 10 business days in Indonesia.
A9: 8 | B9: SYNTH_001 | C9: First-time DTV applicant - Digital Nomad (Remote Worker) | D9: Train | E9: Thanks & closing | F9: No | G9: Yes | H9: Understood. I'll stay put. Thanks for the help! | I9: You're welcome! Our legal team will review your documents and provide feedback in the app. Feel free to reach out if you have any questions. Our working hours are 10 AM to 6 PM Thailand time.
A10: 9 | B10: SYNTH_002 | C10: Thai Cooking Class DTV - First Application | D10: Train | E10: Sharing situation | F10: No | G10: No | H10: Hi! I want to apply for DTV using Thai cooking class. Already enrolled at a school in Chiang Mai. | I10: Hello! That's great that you already have enrollment at a cooking school. May I know your nationality and where you plan to submit your application?
A11: 10 | B11: SYNTH_002 | C11: Thai Cooking Class DTV - First Application | D11: Train | E11: Sharing situation | F11: No | G11: No | H11: I'm from Singapore. Planning to apply from here before traveling to Thailand. | I11: Perfect! Singapore is one of our recommended countries for DTV applications with high approval rates. Since you have your own cooking school enrollment, our service fee is 18,000 THB including all government fees.
A12: 11 | B12: SYNTH_002 | C12: Thai Cooking Class DTV - First Application | D12: Train | E12: Documents | F12: No | G12: No | H12: What documents needed from the cooking school? | I12: From your cooking school, you'll need: 1. Acceptance/Enrollment letter with your name, course dates (should be at least 6 months), and school details 2. Proof of payment for the course 3. The school's business registration The enrollment letter should clearly state the training period dates. Please ensure the dates align with when you plan to enter Thailand.
A13: 12 | B13: SYNTH_002 | C13: Thai Cooking Class DTV - First Application | D13: Train | E13: Documents | F13: Yes | G13: No | H13: My course is from March to August next year. Is 6 months okay? | I13: Yes, 6 months is perfect! That meets the minimum requirement. Please also prepare: 1. Passport with 6+ months validity 2. Bank statements showing 500,000 THB equivalent for 3 months 3. Passport photo 4. Proof of Singapore address
... A129: 128 | B129: SYNTH_015 | C129: Urgent Application - Time Sensitive | D129: Test | E129: Progress update (high intent) | F129: No | G129: No | H129: Amazing! Paying now. Flying to KL day after tomorrow, arriving evening. | I129: Payment received! We'll submit your application as soon as you send us your arrival stamp photo. Safe travels and keep us updated!

Sheet Type rules
A1: Order | B1: Question type | C1: Applies to | D1: Keyword rule (regex, first match wins)
A2: 1 | B2: Rejection & reapplication | C2: Messages with a '?' | D2: reject|reapply|insufficient documentation
A3: 2 | B3: Embassy interview | C3: Messages with a '?' | D3: interview|what questions|not say|what time should i arrive|should i mention
A4: 3 | B4: After approval & staying | C4: Messages with a '?' | D4: approved!|arrival card|printout|re-?enter|each entry|90-day|extend|border run|work for thai|in trouble for being late|report again
A5: 4 | B5: Payment | C5: Messages with a '?' | D5: \bpay\b|payment|transfer|card|receipt|paying
A6: 5 | B6: Fees & guarantee | C6: Messages with a '?' | D6: \bfees?\b|pricing|price|cost|cheaper|how much is|money-back|guarantee|hidden|free\?
A7: 6 | B7: Bank balance & finances | C7: Messages with a '?' | D7: bank|crypto|stocks?|savings|500k|500,000|balance|convert|sgd|usd|\$
A8: 7 | B8: Documents | C8: Messages with a '?' | D8: document|translation|invoice|address|license|photo|records|format|acceptable|missing|6 months okay|need from me|enrollment letter|what do they need|online system
A9: 8 | B9: Timeline & processing | C9: Messages with a '?' | D9: how long|processing|how quickly|budget|accommodation|fastest|hear back|urgent|expires
A10: 9 | B10: DTV rules & eligibility | C10: Messages with a '?' | D10: thai (company|client)|way around|is that a problem
A11: 10 | B11: Where & how to apply | C11: Messages with a '?' | D11: apply|country|embassy|switch|gym|enroll|beginner|muay thai|cooking|freelance|get started|first step|start the process|whatsapp|anything else|upload\?
A12: 11 | B12: Rejection & reapplication | C12: Messages without a '?' | D12: reject|insufficient documentation
A13: 12 | B13: After approval & staying | C13: Messages without a '?' | D13: dtv is approved
... A17: 16 | B17: Sharing situation | C17: Messages without a '?' | D17: .
